CHANGELOG.rst
LICENSE.txt
MANIFEST.in
README.rst
TODO.txt
VERSION.txt
setup.cfg
setup.py
pyramid_iniherit/__init__.py
pyramid_iniherit/install.py
pyramid_iniherit/resolve.py
pyramid_iniherit/scripts.py
pyramid_iniherit.egg-info/PKG-INFO
pyramid_iniherit.egg-info/SOURCES.txt
pyramid_iniherit.egg-info/dependency_links.txt
pyramid_iniherit.egg-info/entry_points.txt
pyramid_iniherit.egg-info/requires.txt
pyramid_iniherit.egg-info/top_level.txt
pyramid_iniherit.egg-info/zip-safe