Metadata-Version: 1.1
Name: pyramid-iniherit
Version: 0.1.9
Summary: Enables pyramid configuration INI file inheritance via the "iniherit" package.
Home-page: http://github.com/cadithealth/pyramid_iniherit
Author: Philip J Grabner, Cadit Health Inc
Author-email: oss@cadit.com
License: MIT (http://opensource.org/licenses/MIT)
Keywords: pyramid configuration INI inheritance
Platform: any
Classifier: Development Status :: 4 - Beta
Classifier: Intended Audience :: Developers
Classifier: Programming Language :: Python
Classifier: Operating System :: OS Independent
Classifier: Natural Language :: English
Classifier: License :: OSI Approved :: MIT License
Classifier: License :: Public Domain
